spotlight/extractor.py
windows_spotlight_extractor-1.0.0.dist-info/LICENSE.md
windows_spotlight_extractor-1.0.0.dist-info/METADATA
windows_spotlight_extractor-1.0.0.dist-info/WHEEL
windows_spotlight_extractor-1.0.0.dist-info/entry_points.txt
windows_spotlight_extractor-1.0.0.dist-info/top_level.txt
windows_spotlight_extractor-1.0.0.dist-info/RECORD
