Metadata-Version: 2.1
Name: windows-spotlight-extractor
Version: 1.0.0
Summary: CLI Tool for exporting Windows 10 Spotlight Images as Wallpapers
Home-page: https://bitbucket.org/Jonathan_Turnock/windows-10-spotlight-extractor
Author: Jonathan Turnock
Author-email: Jonathan.Turnock@outlook.com
License: MIT
Platform: UNKNOWN
Requires-Dist: pillow
